{
  "version": "1.0.0",
  "categories": {
    "greetings": "Greetings & Small Talk",
    "restaurant": "At the Restaurant",
    "shopping": "Shopping",
    "directions": "Asking for Directions",
    "travel": "Travel & Transport",
    "phone": "Phone Conversations"
  },
  "sentences": [
    { "id": "greetings_001", "category": "greetings", "french": "Bonjour, comment allez-vous ?", "english": "Hello, how are you?" },
    { "id": "greetings_002", "category": "greetings", "french": "Je m'appelle Marie, et vous ?", "english": "My name is Marie, and you?" },
    { "id": "greetings_003", "category": "greetings", "french": "Enchanté de faire votre connaissance.", "english": "Nice to meet you." },
    { "id": "greetings_004", "category": "greetings", "french": "Comment ça va aujourd'hui ?", "english": "How are you doing today?" },
    { "id": "greetings_005", "category": "greetings", "french": "Ça fait longtemps qu'on ne s'est pas vus !", "english": "It's been a long time since we last saw each other!" },
    { "id": "greetings_006", "category": "greetings", "french": "Bonsoir, vous allez bien ?", "english": "Good evening, are you doing well?" },
    { "id": "greetings_007", "category": "greetings", "french": "À bientôt, bonne journée !", "english": "See you soon, have a nice day!" },
    { "id": "greetings_008", "category": "greetings", "french": "Salut, quoi de neuf ?", "english": "Hi, what's new?" },
    { "id": "restaurant_001", "category": "restaurant", "french": "Je voudrais un café, s'il vous plaît.", "english": "I would like a coffee, please." },
    { "id": "restaurant_002", "category": "restaurant", "french": "L'addition, s'il vous plaît.", "english": "The check, please." },
    { "id": "restaurant_003", "category": "restaurant", "french": "Est-ce que vous avez une table pour deux ?", "english": "Do you have a table for two?" },
    { "id": "restaurant_004", "category": "restaurant", "french": "Qu'est-ce que vous recommandez ?", "english": "What do you recommend?" },
    { "id": "restaurant_005", "category": "restaurant", "french": "Je suis allergique aux noix.", "english": "I am allergic to nuts." },
    { "id": "restaurant_006", "category": "restaurant", "french": "Puis-je voir le menu, s'il vous plaît ?", "english": "May I see the menu, please?" },
    { "id": "restaurant_007", "category": "restaurant", "french": "Je vais prendre le plat du jour.", "english": "I'll have the dish of the day." },
    { "id": "restaurant_008", "category": "restaurant", "french": "C'était délicieux, merci beaucoup.", "english": "It was delicious, thank you very much." },
    { "id": "shopping_001", "category": "shopping", "french": "Combien ça coûte ?", "english": "How much does it cost?" },
    { "id": "shopping_002", "category": "shopping", "french": "Est-ce que je peux essayer cette taille ?", "english": "Can I try this size?" },
    { "id": "shopping_003", "category": "shopping", "french": "Vous acceptez la carte bancaire ?", "english": "Do you accept credit cards?" },
    { "id": "shopping_004", "category": "shopping", "french": "Je cherche un cadeau pour mon ami.", "english": "I'm looking for a gift for my friend." },
    { "id": "shopping_005", "category": "shopping", "french": "Est-ce qu'il y a une réduction ?", "english": "Is there a discount?" },
    { "id": "shopping_006", "category": "shopping", "french": "Je fais du trente-huit en chaussures.", "english": "I'm a size 38 in shoes." },
    { "id": "shopping_007", "category": "shopping", "french": "Où sont les cabines d'essayage ?", "english": "Where are the fitting rooms?" },
    { "id": "shopping_008", "category": "shopping", "french": "Je voudrais échanger cet article.", "english": "I would like to exchange this item." },
    { "id": "directions_001", "category": "directions", "french": "Excusez-moi, où se trouve la gare ?", "english": "Excuse me, where is the train station?" },
    { "id": "directions_002", "category": "directions", "french": "Tournez à gauche au prochain carrefour.", "english": "Turn left at the next intersection." },
    { "id": "directions_003", "category": "directions", "french": "C'est à cinq minutes à pied d'ici.", "english": "It's a five-minute walk from here." },
    { "id": "directions_004", "category": "directions", "french": "Prenez la deuxième rue à droite.", "english": "Take the second street on the right." },
    { "id": "directions_005", "category": "directions", "french": "Est-ce que c'est loin d'ici ?", "english": "Is it far from here?" },
    { "id": "directions_006", "category": "directions", "french": "Continuez tout droit pendant deux cents mètres.", "english": "Continue straight ahead for two hundred meters." },
    { "id": "directions_007", "category": "directions", "french": "La pharmacie est en face de la boulangerie.", "english": "The pharmacy is across from the bakery." },
    { "id": "directions_008", "category": "directions", "french": "Je suis perdu, pouvez-vous m'aider ?", "english": "I'm lost, can you help me?" },
    { "id": "travel_001", "category": "travel", "french": "À quelle heure part le prochain train ?", "english": "What time does the next train leave?" },
    { "id": "travel_002", "category": "travel", "french": "Je voudrais un billet aller-retour.", "english": "I would like a round-trip ticket." },
    { "id": "travel_003", "category": "travel", "french": "Où est l'arrêt de bus le plus proche ?", "english": "Where is the nearest bus stop?" },
    { "id": "travel_004", "category": "travel", "french": "Le vol a été retardé de deux heures.", "english": "The flight has been delayed by two hours." },
    { "id": "travel_005", "category": "travel", "french": "J'ai réservé une chambre pour trois nuits.", "english": "I booked a room for three nights." },
    { "id": "travel_006", "category": "travel", "french": "Où puis-je récupérer mes bagages ?", "english": "Where can I pick up my luggage?" },
    { "id": "travel_007", "category": "travel", "french": "Est-ce que le petit déjeuner est inclus ?", "english": "Is breakfast included?" },
    { "id": "travel_008", "category": "travel", "french": "Je voudrais louer une voiture pour la semaine.", "english": "I would like to rent a car for the week." },
    { "id": "phone_001", "category": "phone", "french": "Allô, est-ce que je pourrais parler à Monsieur Dupont ?", "english": "Hello, could I speak to Mr. Dupont?" },
    { "id": "phone_002", "category": "phone", "french": "Je vous rappelle dans cinq minutes.", "english": "I'll call you back in five minutes." },
    { "id": "phone_003", "category": "phone", "french": "Pouvez-vous répéter, s'il vous plaît ?", "english": "Can you repeat that, please?" },
    { "id": "phone_004", "category": "phone", "french": "La ligne est mauvaise, je vous entends mal.", "english": "The connection is bad, I can barely hear you." },
    { "id": "phone_005", "category": "phone", "french": "Je voudrais prendre rendez-vous.", "english": "I would like to make an appointment." },
    { "id": "phone_006", "category": "phone", "french": "Vous avez fait un faux numéro.", "english": "You have the wrong number." },
    { "id": "phone_007", "category": "phone", "french": "Ne quittez pas, je vous mets en attente.", "english": "Hold on, I'm putting you on hold." },
    { "id": "phone_008", "category": "phone", "french": "Merci d'avoir appelé, au revoir.", "english": "Thank you for calling, goodbye." }
  ]
}
